packaging_tutorial_homeless/__init__.py
packaging_tutorial_homeless/py.typed
packaging_tutorial_homeless-0.1.0.dist-info/METADATA
packaging_tutorial_homeless-0.1.0.dist-info/WHEEL
packaging_tutorial_homeless-0.1.0.dist-info/RECORD
